LICENSE
README.md
setup.py
sound4_directory_listing.egg-info/PKG-INFO
sound4_directory_listing.egg-info/SOURCES.txt
sound4_directory_listing.egg-info/dependency_links.txt
sound4_directory_listing.egg-info/entry_points.txt
sound4_directory_listing.egg-info/requires.txt
sound4_directory_listing.egg-info/top_level.txt
sound4directorylisting/main.py
sound4directorylisting/includes/__init__.py
sound4directorylisting/includes/bot.py
sound4directorylisting/includes/filereader.py
sound4directorylisting/includes/scan.py
sound4directorylisting/includes/writefile.py
sound4directorylisting/utils/__init__.py
sound4directorylisting/utils/configure.py
sound4directorylisting/utils/const.py
sound4directorylisting/utils/helpers.py
sound4directorylisting/utils/status.py